z3c.testing-1.0.0-py3.9-nspkg.pth
z3c/testing/BROWSER.txt
z3c/testing/__init__.py
z3c/testing/app.py
z3c/testing/directive.py
z3c/testing/generation.py
z3c/testing/layer.py
z3c/testing/test.zcml
z3c/testing/tests.py
z3c.testing-1.0.0.dist-info/METADATA
z3c.testing-1.0.0.dist-info/WHEEL
z3c.testing-1.0.0.dist-info/namespace_packages.txt
z3c.testing-1.0.0.dist-info/top_level.txt
z3c.testing-1.0.0.dist-info/RECORD
