Metadata-Version: 2.1
Name: z3c.testing
Version: 1.0.0
Summary: High-level Testing Support
Home-page: http://pypi.python.org/pypi/z3c.testing
Author: Zope Corporation and Contributors
Author-email: zope-dev@zope.org
License: ZPL 2.1
Keywords: zope3 testing layer zodb
Platform: UNKNOWN
Classifier: Development Status :: 5 - Production/Stable
Classifier: Environment :: Web Environment
Classifier: Intended Audience :: Developers
Classifier: License :: OSI Approved :: Zope Public License
Classifier: Programming Language :: Python :: 2
Classifier: Programming Language :: Python :: 2.7
Classifier: Programming Language :: Python :: 3
Classifier: Programming Language :: Python :: 3.5
Classifier: Programming Language :: Python :: 3.6
Classifier: Programming Language :: Python :: 3.7
Classifier: Programming Language :: Python :: 3.8
Classifier: Programming Language :: Python :: 3.9
Classifier: Programming Language :: Python :: 3.10
Classifier: Programming Language :: Python :: Implementation :: CPython
Classifier: Programming Language :: Python :: Implementation :: PyPy
Classifier: Natural Language :: English
Classifier: Operating System :: OS Independent
Classifier: Topic :: Internet :: WWW/HTTP
Classifier: Framework :: Zope :: 3
Requires-Dist: setuptools
Requires-Dist: zope.container
Requires-Dist: zope.site
Requires-Dist: zope.security
Requires-Dist: zope.component
Requires-Dist: zope.configuration
Requires-Dist: zope.interface (>=4.0.5)
Requires-Dist: zope.testing
Provides-Extra: functional
Requires-Dist: ZODB3 ; extra == 'functional'
Requires-Dist: zope.app.rotterdam ; extra == 'functional'
Requires-Dist: zope.app.appsetup ; extra == 'functional'
Requires-Dist: zope.app.publication ; extra == 'functional'
Requires-Dist: zope.app.testing ; extra == 'functional'
Requires-Dist: zope.testbrowser (<5) ; extra == 'functional'
Provides-Extra: test
Requires-Dist: zope.browserpage ; extra == 'test'
Requires-Dist: zope.browserresource ; extra == 'test'
Requires-Dist: zope.principalregistry ; extra == 'test'
Requires-Dist: zope.publisher ; extra == 'test'
Requires-Dist: zope.securitypolicy ; extra == 'test'
Requires-Dist: zope.testrunner ; extra == 'test'
